ntypes/__init__.py
ntypes/ntypes_pb2.py
protobuf_ntypes-1.3.0.dist-info/LICENSE.txt
protobuf_ntypes-1.3.0.dist-info/METADATA
protobuf_ntypes-1.3.0.dist-info/WHEEL
protobuf_ntypes-1.3.0.dist-info/top_level.txt
protobuf_ntypes-1.3.0.dist-info/RECORD
