Metadata-Version: 2.1
Name: protobuf-ntypes
Version: 1.3.0
Summary: protobuf nilable data structures
Home-page: https://github.com/piotrkowalczuk/ntypes
Author: Piotr Kowalczuk
Author-email: p.kowalczuk.priv@gmail.com
License: MIT
Download-URL: https://github.com/piotrkowalczuk/ntypes/archive/v1.3.0.tar.gz
Keywords: protobuf,data-structures,grpc
Platform: UNKNOWN
Classifier: Development Status :: 5 - Production/Stable
Classifier: Intended Audience :: Developers
Classifier: Topic :: Software Development :: Libraries :: Application Frameworks
Classifier: License :: OSI Approved :: MIT License
Classifier: Programming Language :: Python
Classifier: Programming Language :: Python :: 2
Classifier: Programming Language :: Python :: 2.7
Classifier: Programming Language :: Python :: 3
Classifier: Programming Language :: Python :: 3.4
Classifier: Programming Language :: Python :: 3.5
Classifier: Programming Language :: Python :: 3.6
Requires-Dist: protobuf
